mulder/__init__.py
mulder/__main__.py
mulder/_core.abi3.so
mulder/data/geoid/egm96.png
mulder/data/magnet/IGRF14.COF
mulder/interface/LICENSE
mulder/interface/mulder.h
mulder/interface/geant4/G4Mulder.cc
mulder/interface/geant4/G4Mulder.hh
mulder/interface/geant4/mulder.h
mulder/materials/__init__.py
mulder/picture/__init__.py
mulder-0.3.2.dist-info/COPYING.LESSER
mulder-0.3.2.dist-info/LICENSE
mulder-0.3.2.dist-info/METADATA
mulder-0.3.2.dist-info/WHEEL
mulder-0.3.2.dist-info/entry_points.txt
mulder-0.3.2.dist-info/top_level.txt
mulder-0.3.2.dist-info/RECORD
