Metadata-Version: 2.4
Name: mulder
Version: 0.3.2
Summary: MUon fLuxme'DER
Author-email: Valentin Niess <valentin.niess@gmail.com>
License: LGPL-3.0-or-later
Project-URL: homepage, https://github.com/niess/mulder
Project-URL: documentation, https://mulder.readthedocs.io
Project-URL: download, https://pypi.python.org/pypi/mulder
Project-URL: source, https://github.com/niess/mulder
Project-URL: issues, https://github.com/niess/mulder/issues
Classifier: Development Status :: 3 - Alpha
Classifier: Intended Audience :: Science/Research
Classifier: Topic :: Scientific/Engineering :: Physics
Requires-Python: >=3.8
License-File: LICENSE
License-File: COPYING.LESSER
Requires-Dist: numpy>=1.6.0
Dynamic: license-file
